morse_text_miked/__init__.py
morse_text_miked/morse_text.py
morse_text_miked-0.2.dist-info/METADATA
morse_text_miked-0.2.dist-info/WHEEL
morse_text_miked-0.2.dist-info/licenses/LICENSE
morse_text_miked-0.2.dist-info/RECORD
