Metadata-Version: 2.1
Name: morse_text_miked
Version: 0.2
Summary: A Text to Morse and back console auto converter
Project-URL: Homepage, https://github.com/mike0618/Portfolio_Projects/tree/1_Text_to_Morse_Miked
Project-URL: Bug Tracker, https://github.com/mike0618/Portfolio_Projects/issues
Author-email: "miked (Mike Zubko)" <mike0618dev@yahoo.com>
License: Copyright (c) 2018 The Python Packaging Authority
Classifier: License :: OSI Approved :: MIT License
Classifier: Operating System :: OS Independent
Classifier: Programming Language :: Python :: 3
Requires-Python: >=3.7
